generated_package/__init__.py
generated_package/cities.json
generated_package/states_info.py
generated_repo_3-0.0.0.dist-info/METADATA
generated_repo_3-0.0.0.dist-info/WHEEL
generated_repo_3-0.0.0.dist-info/top_level.txt
generated_repo_3-0.0.0.dist-info/RECORD
