Metadata-Version: 2.4
Name: generated-repo-3
Version: 0.0.0
Summary: My package description
Author-email: Eric Riddoch <some-email@gmail.com>
License: MIT
Keywords: one,two
Classifier: Programming Language :: Python :: 3
Requires-Python: >=3.7
Requires-Dist: numpy
Requires-Dist: importlib-metadata; python_version < "3.8"
Provides-Extra: test
Requires-Dist: pytest; extra == "test"
Requires-Dist: pytest-cov; extra == "test"
Provides-Extra: release
Requires-Dist: build; extra == "release"
Requires-Dist: twine; extra == "release"
Provides-Extra: static-code-qa
Requires-Dist: pre-commit; extra == "static-code-qa"
Provides-Extra: dev
Requires-Dist: generated-repo-3[release,static-code-qa,test]; extra == "dev"
